swamix/ai.py
swamix/ai_utils.py
swamix/classes.py
swamix/copilot.pyw
swamix/copilot_run.ps1
swamix/db.py
swamix/ENUMS_MODELS.py
swamix/html_engine.py
swamix/microphone_icon.jpg
swamix/mydict.json
swamix/platforms/__init__.py
swamix/platforms/oci_test.py
swamix/platforms/oracle.py
swamix/temp.md
swamix/terminal.txt
swamix/trials_scraper.py
swamix/utils.py
swamix/web.py
swamix-0.4.0.dist-info/METADATA
swamix-0.4.0.dist-info/WHEEL
swamix-0.4.0.dist-info/RECORD
