Metadata-Version: 2.1
Name: swamix
Version: 0.4.0
Summary: swamix.com official library, by your techie Nikhil Swami
License: Free to use for entities/individuals whose annual revenue do not exceed $250,000
Author: M Nikhil Swami
Author-email: nikhil@swamix.com
Requires-Python: >=3.8,<4.0
Classifier: License :: Other/Proprietary License
Classifier: Programming Language :: Python :: 3
Classifier: Programming Language :: Python :: 3.8
Classifier: Programming Language :: Python :: 3.9
Classifier: Programming Language :: Python :: 3.10
Classifier: Programming Language :: Python :: 3.11
Classifier: Programming Language :: Python :: 3.12
Requires-Dist: colorama
Requires-Dist: openai (>=1.52.0,<2.0.0)
Requires-Dist: playwright
Requires-Dist: pyautogui (>=0.9.54,<0.10.0)
Requires-Dist: requests
Requires-Dist: selectolax
